red_green_refactor_widget/__init__.py
red_green_refactor_widget/app.py
red_green_refactor_widget/cli.py
red_green_refactor_widget/debug.py
red_green_refactor_widget/ui.py
red_green_refactor_widget/window.ui
tests/__init__.py
tests/tests.py
red_green_refactor_widget-0.0.1.dist-info/LICENSE
red_green_refactor_widget-0.0.1.dist-info/METADATA
red_green_refactor_widget-0.0.1.dist-info/WHEEL
red_green_refactor_widget-0.0.1.dist-info/entry_points.txt
red_green_refactor_widget-0.0.1.dist-info/top_level.txt
red_green_refactor_widget-0.0.1.dist-info/RECORD
