Metadata-Version: 2.1
Name: red-green-refactor-widget
Version: 0.0.1
Summary: A simple widget that will help you to stick to the red-green-refactor workflow
Home-page: http://github.com/mode89/red-green-refactor-widget
Author: Andrey Krainyak
Author-email: mode.andrew@gmail.com
License: UNKNOWN
Platform: UNKNOWN
Classifier: Programming Language :: Python :: 3
Classifier: License :: OSI Approved :: MIT License
Classifier: Operating System :: OS Independent
Requires-Python: >=3.6
Requires-Dist: PyQt5
Requires-Dist: pyqtkeybind
